gcmt3d/__init__.py
gcmt3d/inversion.py
gcmt3d/log_util.py
gcmt3d/source.py
gcmt3d/asdf/__init__.py
gcmt3d/asdf/add_traces.py
gcmt3d/asdf/convert.py
gcmt3d/asdf/procbase.py
gcmt3d/asdf/process.py
gcmt3d/asdf/stations.py
gcmt3d/asdf/utils.py
gcmt3d/asdf/window.py
gcmt3d/bins/__init__.py
gcmt3d/bins/compute_stats.py
gcmt3d/bins/convert_to_asdf.py
gcmt3d/bins/convert_to_sac.py
gcmt3d/bins/count_overall_windows.py
gcmt3d/bins/create_entry.py
gcmt3d/bins/create_path_files.py
gcmt3d/bins/extract_station_info.py
gcmt3d/bins/filter_windows.py
gcmt3d/bins/generate_stations_asdf.py
gcmt3d/bins/gridsearch.py
gcmt3d/bins/inversion.py
gcmt3d/bins/process_asdf.py
gcmt3d/bins/request_data.py
gcmt3d/bins/window_selection_asdf.py
gcmt3d/bins/write_grid_search_dicts.py
gcmt3d/bins/write_inversion_dicts.py
gcmt3d/bins/write_sources.py
gcmt3d/data/__init__.py
gcmt3d/data/download/__init__.py
gcmt3d/data/download/requestBuilder.py
gcmt3d/data/download/resources/Fetchdata
gcmt3d/data/download/resources/stations.txt
gcmt3d/data/management/STATIONS
gcmt3d/data/management/__init__.py
gcmt3d/data/management/create_process_paths.py
gcmt3d/data/management/inversion_dicts.py
gcmt3d/data/management/skeleton.py
gcmt3d/data/management/specfem_sources.py
gcmt3d/plot/__init__.py
gcmt3d/plot/plot_util.py
gcmt3d/plot/stats.py
gcmt3d/runSF3D/__init__.py
gcmt3d/runSF3D/runSF3D.py
gcmt3d/runSF3D/batch/drive.sbatch
gcmt3d/runSF3D/batch/drive.sh
gcmt3d/signal/__init__.py
gcmt3d/signal/compare_trace.py
gcmt3d/signal/convolve.py
gcmt3d/signal/process.py
gcmt3d/signal/rotate.py
gcmt3d/signal/rotate_utils.py
gcmt3d/station/__init__.py
gcmt3d/station/extract_staxml_info.py
gcmt3d/station/generate_adjoint_stations.py
gcmt3d/station/utils.py
gcmt3d/stats/__init__.py
gcmt3d/stats/stats.py
gcmt3d/stf_inversion/__init__.py
gcmt3d/stf_inversion/blub_test_source_inversion.py
gcmt3d/stf_inversion/forward.py
gcmt3d/stf_inversion/plot.py
gcmt3d/stf_inversion/plot_util.py
gcmt3d/stf_inversion/stf.py
gcmt3d-0.0.2.dist-info/METADATA
gcmt3d-0.0.2.dist-info/WHEEL
gcmt3d-0.0.2.dist-info/entry_points.txt
gcmt3d-0.0.2.dist-info/top_level.txt
gcmt3d-0.0.2.dist-info/RECORD
