Metadata-Version: 2.1
Name: gcmt3d
Version: 0.0.2
Summary: Global 3D Centroid Moment Tensor Inversion
Home-page: https://github.com/lsawade/GCMT3D
Author: Lucas Sawade
Author-email: lsawade@princeton.edu
License: GNU Lesser General Public License, Version 3
Keywords: Global CMT,Inversion,Moment Tensor
Platform: UNKNOWN
Classifier: Development Status :: 4 - Beta
Classifier: Topic :: Utilities
Classifier: License :: OSI Approved :: GNU General Public License v3 or later (GPLv3+)
Requires-Dist: numpy
Requires-Dist: matplotlib
Requires-Dist: flake8
Requires-Dist: obspy (==1.1.1)
Requires-Dist: PyYAML
Requires-Dist: pyflex
Requires-Dist: h5py
Requires-Dist: mpi4py
Requires-Dist: pyasdf
Requires-Dist: spaceweight
Requires-Dist: pycmt3d
Provides-Extra: docs
Requires-Dist: sphinx ; extra == 'docs'
Requires-Dist: sphinx-rtd-theme ; extra == 'docs'
Provides-Extra: tests
Requires-Dist: pytest ; extra == 'tests'
Requires-Dist: py ; extra == 'tests'
